{
  "version": "7",
  "dialect": "mysql",
  "entries": [
    {
      "idx": 0,
      "version": "5",
      "when": 1778934526312,
      "tag": "0000_overjoyed_otto_octavius",
      "breakpoints": true
    },
    {
      "idx": 1,
      "version": "5",
      "when": 1779079741723,
      "tag": "0001_sharp_colossus",
      "breakpoints": true
    },
    {
      "idx": 2,
      "version": "5",
      "when": 1779080059207,
      "tag": "0002_equal_cammi",
      "breakpoints": true
    },
    {
      "idx": 3,
      "version": "5",
      "when": 1781530039721,
      "tag": "0003_grey_wiccan",
      "breakpoints": true
    },
    {
      "idx": 4,
      "version": "5",
      "when": 1782138537637,
      "tag": "0004_naive_tag",
      "breakpoints": true
    }
  ]
}